__init__.py
core/__init__.py
core/collision/__init__.py
core/collision/base.py
core/collision/collision_BGK.py
core/collision/collision_MRT.py
core/collision/source.py
core/grid/__init__.py
core/grid/grid.py
core/lattice/__init__.py
core/lattice/lattice.py
core/run/__init__.py
core/run/run.py
core/simulation/__init__.py
core/simulation/base.py
core/simulation/multi_phase.py
core/simulation/single_phase.py
core/stream/__init__.py
core/stream/stream.py
core/update/__init__.py
core/update/update.py
core/update/update_multiphase.py
core/update/update_multiphase_hysteresis.py
operators/__init__.py
operators/boundary_condition/__init__.py
operators/boundary_condition/boundary_condition.py
operators/differential/__init__.py
operators/differential/gradient.py
operators/differential/laplacian.py
operators/equilibrium/__init__.py
operators/equilibrium/equilibrium.py
operators/force/__init__.py
operators/force/composite_force.py
operators/force/electric_force.py
operators/force/force.py
operators/force/gravitational_force.py
operators/initialise/__init__.py
operators/initialise/initilise.py
operators/macroscopic/__init__.py
operators/macroscopic/macroscopic.py
operators/macroscopic/macroscopic_multiphase_cs.py
operators/macroscopic/macroscopic_multiphase_dw.py
operators/wetting/__init__.py
operators/wetting/contact_angle.py
operators/wetting/contact_line_location.py
operators/wetting/wetting_util.py
tud_lbm-2026.0.0a1.dist-info/licenses/LICENSE
tud_lbm-2026.0.0a1.dist-info/licenses/NOTICE
util/__init__.py
util/io.py
util/plotting.py
tud_lbm-2026.0.0a1.dist-info/METADATA
tud_lbm-2026.0.0a1.dist-info/WHEEL
tud_lbm-2026.0.0a1.dist-info/top_level.txt
tud_lbm-2026.0.0a1.dist-info/RECORD
